MANIFEST.in
README.rst
setup.cfg
setup.py
deps/core.txt
deps/doc.txt
deps/test.txt
pylease/__init__.py
pylease/ctxmgmt.py
pylease/ex.py
pylease/filemgmt.py
pylease/logger.py
pylease/main.py
pylease/releasemgmt.py
pylease/util.py
pylease/vermgmt.py
pylease.egg-info/PKG-INFO
pylease.egg-info/SOURCES.txt
pylease.egg-info/dependency_links.txt
pylease.egg-info/entry_points.txt
pylease.egg-info/top_level.txt
pylease/cmd/__init__.py
pylease/cmd/rollback.py
pylease/cmd/task.py
pylease/ext/__init__.py
pylease/ext/git.py
pylease/ext/pypi.py
tests/__init__.py
tests/test_command.py
tests/test_ctxmgmt.py
tests/test_filemgmt.py
tests/test_main.py
tests/test_releasemgmt.py
tests/test_rollback.py
tests/test_util.py
tests/test_vermgmt.py